README.md
setup.cfg
setup.py
TOPSIS/__init__.py
TOPSIS/__main__.py
Topsis_Aditi_102003512.egg-info/PKG-INFO
Topsis_Aditi_102003512.egg-info/SOURCES.txt
Topsis_Aditi_102003512.egg-info/dependency_links.txt
Topsis_Aditi_102003512.egg-info/entry_points.txt
Topsis_Aditi_102003512.egg-info/top_level.txt