Metadata-Version: 2.1
Name: Topsis-Aditi-102003512
Version: 1.0.1
Summary: Calculate TOPSIS Ranks
Home-page: https://github.com/aditisingh-20/Topsis-Aditi-102003512/tree/v_01
Author: Aditi Singh
Author-email: asingh7_be20@thapar.edu
License: MIT
Download-URL: https://github.com/aditisingh-20/Topsis-Aditi-102003512/archive/refs/tags/v_01.tar.gz
Platform: UNKNOWN
Classifier: License :: OSI Approved :: MIT License
Classifier: Programming Language :: Python :: 3.6
Classifier: Programming Language :: Python :: 3.7
Classifier: Programming Language :: Python :: 3.8
